{
  "id": "seedstars-world-competition",
  "provider": "Seedstars",
  "title": "Seedstars World Competition",
  "category": "competitions-hackathons",
  "subcategories": [
    "startup-competitions",
    "pitch-competitions"
  ],
  "tags": [
    "startups",
    "pitch"
  ],
  "description": "Seedstars World Competition is a startup competition from Seedstars in which selected founders pitch their ventures to judges, investors, or a conference audience.",
  "eligibility": "Participants must meet the current age, location, team, entry, conduct, intellectual-property, and deadline requirements.",
  "value": "Pitch exposure and competition-specific funding, prizes, or investor access",
  "sourceUrl": "https://www.seedstars.com/community/entrepreneurs/",
  "officialUrl": "https://www.seedstars.com/community/entrepreneurs/",
  "status": "limited",
  "submissionType": "maintainer",
  "sponsor": false,
  "reviewDate": "2026-07-18",
  "regions": [
    "Global"
  ]
}
